Workbook

Sheet Lisez-moi
B2: Rikolto RDC · Café & Cacao — classeur du tableau de bord
B3: Version Excel du dashboard Power BI (5 pages), préparée en septembre 2026.
B5: Comment l'utiliser
B6: • Onglet Dashboard : choisissez une campagne et une coopérative dans les cellules jaunes C4 et C5. Tous les indicateurs café se recalculent.
B7: • Les graphiques par campagne suivent le filtre Coopérative. Les indicateurs cacao portent sur les 88 ménages de l'enquête.
B8: • Texte bleu = donnée source (à ne modifier qu'en cas de correction de la base). Texte noir = formule.
B10: Onglets
B11: • Dashboard : indicateurs clés, 6 graphiques, profil des coopératives et messages clés.
B12: • Séries : tables calculées qui alimentent les graphiques (par campagne, par section, composition du revenu).
B13: • Café_données : base café agrégée par campagne et coopérative (20 lignes issues des 42 433 lignes producteurs).
B14: • Cacao_ménages : les 88 ménages de l'enquête revenu vital, une ligne par ménage.
B15: • Okapi : liste des 301 planteurs agrégée par section. • Qualité : registre des 23 contrôles. • Paramètres : seuils et sources.
... B22: • Enquête cacao : 88 ménages dont 6 dirigés par des femmes ; résultats indicatifs, à ne pas extrapoler par sous-groupe.

Sheet Dashboard
B1: Rikolto RDC · Café & Cacao — Tableau de bord direction
B2: Campagnes café 2019-2025 · enquête revenu vital cacao, mars 2024 · seuil Anker RDC rurale 2025. Analyse septembre 2026.
B4: Campagne | C4: Toutes | D4: Choisissez une campagne et une coopérative dans les cellules jaunes : les indicateurs café et le profil des coopératives se recalculent. Les graphiques par campagne suivent le filtre Coopérative.
B5: Coopérative | C5: Toutes
B7: Café · bénéficiaires et économie (selon les filtres)
B8: Personnes | C8: Inscriptions | D8: Nouveaux producteurs | E8: Rétention vs N-1 | F8: Femmes | G8: Jeunes 15-35 ans | I8: Contrôles qualité | J8: Critiques | K8: Gravité élevée
B9: =INDEX(Séries!$B$32:$F$39,MATCH(IF(Dashboard!$C$4="Toutes","Toutes",TEXT(Dashboard!$C$4,"0")),Séries!$A$32:$A$39,0),MATCH(Dashboard!$C$5,Séries!$B$31:$F$31,0)) -> 12833 | C9: =SUMIFS(Café_données!$C$3:$C$22,Café_données!$A$3:$A$22,Séries!$B$1,Café_données!$B$3:$B$22,Séries!$B$2) -> 42433 | D9: =SUMIFS(Café_données!$O$3:$O$22,Café_données!$A$3:$A$22,Séries!$B$1,Café_données!$B$3:$B$22,Séries!$B$2) -> 12833 | E9: =IF(SUMIFS(Café_données!$C$3:$C$22,Café_données!$T$3:$T$22,Séries!$B$3-1,Café_données!$B$3:$B$22,Séries!$B$2)<Paramètres!$B$7,"–",SUMIFS(Café_données!$P$3:$P$22,Café_données!$T$3:$T$22,Séries!$B$3,Café_données!$B$3:$B$22,Séries!$B$2)/SUMIFS(Café_données!$C$3:$C$22,Café_données!$T$3:$T$22,Séries!$B$3-1,Café_données!$B$3:$B$22,Séries!$B$2)) -> 0.99592537 | F9: =IFERROR(SUMIFS(Café_données!$D$3:$D$22,Café_données!$A$3:$A$22,Séries!$B$1,Café_données!$B$3:$B$22,Séries!$B$2)/SUMIFS(Café_données!$C$3:$C$22,Café_données!$A$3:$A$22,Séries!$B$1,Café_données!$B$3:$B$22,Séries!$B$2),0) -> 0.22694601 | G9: =IFERROR(SUMIFS(Café_données!$E$3:$E$22,Café_données!$A$3:$A$22,Séries!$B$1,Café_données!$B$3:$B$22,Séries!$B$2)/SUMIFS(Café_données!$C$3:$C$22,Café_données!$A$3:$A$22,Séries!$B$1,Café_données!$B$3:$B$22,Séries!$B$2),0) -> 0.44884877 | I9: =COUNTA(Qualité!$D$4:$D$26) -> 23 | J9: =COUNTIF(Qualité!$H$4:$H$26,"Critique") -> 4 | K9: =COUNTIF(Qualité!$H$4:$H$26,"Élevée") -> 7
B10: Identifiant longitudinal | C10: 1 ligne = 1 producteur × campagne | E10: Dernière campagne sélectionnée ; – si OP nouvelle | G10: Rapporté à tous les producteurs | I10: Registre complet : onglet Qualité
B11: Superficie déclarée (ha) | C11: Superficie moyenne (ha) | D11: Certifiés conformes | E11: Production estimée (t cerise) | F11: CA estimé (M USD) | G11: Marge estimée / producteur (USD) | I11: Territoire renseigné (café) | J11: Cartes en doublon (café)
B12: =SUMIFS(Café_données!$G$3:$G$22,Café_données!$A$3:$A$22,Séries!$B$1,Café_données!$B$3:$B$22,Séries!$B$2) -> 23550.5 | C12: =IFERROR(SUMIFS(Café_données!$G$3:$G$22,Café_données!$A$3:$A$22,Séries!$B$1,Café_données!$B$3:$B$22,Séries!$B$2)/SUMIFS(Café_données!$C$3:$C$22,Café_données!$A$3:$A$22,Séries!$B$1,Café_données!$B$3:$B$22,Séries!$B$2),0) -> 0.55500436 | D12: =IFERROR(SUMIFS(Café_données!$K$3:$K$22,Café_données!$A$3:$A$22,Séries!$B$1,Café_données!$B$3:$B$22,Séries!$B$2)/SUMIFS(Café_données!$C$3:$C$22,Café_données!$A$3:$A$22,Séries!$B$1,Café_données!$B$3:$B$22,Séries!$B$2),0) -> 0.71458535 | E12: =SUMIFS(Café_données!$H$3:$H$22,Café_données!$A$3:$A$22,Séries!$B$1,Café_données!$B$3:$B$22,Séries!$B$2) -> 81063.82 | F12: =SUMIFS(Café_données!$I$3:$I$22,Café_données!$A$3:$A$22,Séries!$B$1,Café_données!$B$3:$B$22,Séries!$B$2)/1000000 -> 44.585107 | G12: =IFERROR(SUMIFS(Café_données!$J$3:$J$22,Café_données!$A$3:$A$22,Séries!$B$1,Café_données!$B$3:$B$22,Séries!$B$2)/SUMIFS(Café_données!$C$3:$C$22,Café_données!$A$3:$A$22,Séries!$B$1,Café_données!$B$3:$B$22,Séries!$B$2),0) -> 630.43058 | I12: =SUM(Café_données!$Q$3:$Q$22)/SUM(Café_données!$C$3:$C$22) -> 0.63636792 | J12: =SUM(Café_données!$R$3:$R$22)/SUM(Café_données!$C$3:$C$22) -> 0.049466217
C13: Donnée déclarée, la plus fiable | E13: ESTIMÉE par paramètres fixes | F13: ESTIMÉ : production × 0,55 USD/kg | G13: Forfait : 60 % du CA | I13: Toutes campagnes | J13: Toutes campagnes
B15: Cacao · revenu des ménages et écart au revenu vital (88 ménages)
B16: Revenu net médian (USD/an) | C16: Seuil revenu vital (USD/an) | D16: Au-dessus du seuil (réf.) | E16: Au-dessus du seuil ajusté | F16: Écart médian au seuil ajusté (USD) | G16: Revenu / pers. / jour (USD) | H16: Part du cacao dans le revenu | I16: Sous 2,15 USD/pers./jour | J16: Dépenses > revenu | K16: Personnes par ménage
B17: =MEDIAN(Cacao_ménages!$H$3:$H$90) -> 3300.5 | C17: =Paramètres!$B$4 -> 2628 | D17: =AVERAGE(Cacao_ménages!$J$3:$J$90) -> 0.59090909 | E17: =AVERAGE(Cacao_ménages!$K$3:$K$90) -> 0.39772727 | F17: {=MEDIAN(IF(Cacao_ménages!$H$3:$H$90<Cacao_ménages!$I$3:$I$90,Cacao_ménages!$I$3:$I$90-Cacao_ménages!$H$3:$H$90))} -> 2225 | G17: =MEDIAN(Cacao_ménages!$L$3:$L$90) -> 0.966 | H17: =SUM(Cacao_ménages!$N$3:$N$90)/SUM(Cacao_ménages!$H$3:$H$90) -> 0.86607275 | I17: =COUNTIF(Cacao_ménages!$L$3:$L$90,"<"&Paramètres!$B$6)/COUNT(Cacao_ménages!$H$3:$H$90) -> 0.79545455 | J17: =COUNTIF(Cacao_ménages!$M$3:$M$90,"<0")/COUNT(Cacao_ménages!$H$3:$H$90) -> 0.18181818 | K17: =AVERAGE(Cacao_ménages!$D$3:$D$90) -> 10.329545
C18: Anker 2025, ménage de 6 | E18: Seuil proportionnel à la taille | F18: Ménages sous le seuil | G18: Médiane | K18: Contre 6 (référence)
B69: Profil des coopératives (selon le filtre Campagne)
B70: Coopérative | C70: Producteurs | D70: Femmes | E70: Jeunes 15-35 | F70: Ha moyen | G70: Certifiés conformes | H70: Rétention vs N-1
B71: CKK | C71: =SUMIFS(Café_données!$C$3:$C$22,Café_données!$A$3:$A$22,Séries!$B$1,Café_données!$B$3:$B$22,$B71) -> 17332 | D71: =IFERROR(SUMIFS(Café_données!$D$3:$D$22,Café_données!$A$3:$A$22,Séries!$B$1,Café_données!$B$3:$B$22,$B71)/SUMIFS(Café_données!$C$3:$C$22,Café_données!$A$3:$A$22,Séries!$B$1,Café_données!$B$3:$B$22,$B71),0) -> 0.29131087 | E71: =IFERROR(SUMIFS(Café_données!$E$3:$E$22,Café_données!$A$3:$A$22,Séries!$B$1,Café_données!$B$3:$B$22,$B71)/SUMIFS(Café_données!$C$3:$C$22,Café_données!$A$3:$A$22,Séries!$B$1,Café_données!$B$3:$B$22,$B71),0) -> 0.4166282 | F71: =IFERROR(SUMIFS(Café_données!$G$3:$G$22,Café_données!$A$3:$A$22,Séries!$B$1,Café_données!$B$3:$B$22,$B71)/SUMIFS(Café_données!$C$3:$C$22,Café_données!$A$3:$A$22,Séries!$B$1,Café_données!$B$3:$B$22,$B71),0) -> 0.55438611 | G71: =IFERROR(SUMIFS(Café_données!$K$3:$K$22,Café_données!$A$3:$A$22,Séries!$B$1,Café_données!$B$3:$B$22,$B71)/SUMIFS(Café_données!$C$3:$C$22,Café_données!$A$3:$A$22,Séries!$B$1,Café_données!$B$3:$B$22,$B71),0) -> 0.73880683 | H71: =IF(SUMIFS(Café_données!$C$3:$C$22,Café_données!$T$3:$T$22,Séries!$B$3-1,Café_données!$B$3:$B$22,$B71)<Paramètres!$B$7,"–",SUMIFS(Café_données!$P$3:$P$22,Café_données!$T$3:$T$22,Séries!$B$3,Café_données!$B$3:$B$22,$B71)/SUMIFS(Café_données!$C$3:$C$22,Café_données!$T$3:$T$22,Séries!$B$3-1,Café_données!$B$3:$B$22,$B71)) -> 0.98841987
B72: COOKKANZ | C72: =SUMIFS(Café_données!$C$3:$C$22,Café_données!$A$3:$A$22,Séries!$B$1,Café_données!$B$3:$B$22,$B72) -> 15628 | D72: =IFERROR(SUMIFS(Café_données!$D$3:$D$22,Café_données!$A$3:$A$22,Séries!$B$1,Café_données!$B$3:$B$22,$B72)/SUMIFS(Café_données!$C$3:$C$22,Café_données!$A$3:$A$22,Séries!$B$1,Café_données!$B$3:$B$22,$B72),0) -> 0.1244561 | E72: =IFERROR(SUMIFS(Café_données!$E$3:$E$22,Café_données!$A$3:$A$22,Séries!$B$1,Café_données!$B$3:$B$22,$B72)/SUMIFS(Café_données!$C$3:$C$22,Café_données!$A$3:$A$22,Séries!$B$1,Café_données!$B$3:$B$22,$B72),0) -> 0.45738418 | F72: =IFERROR(SUMIFS(Café_données!$G$3:$G$22,Café_données!$A$3:$A$22,Séries!$B$1,Café_données!$B$3:$B$22,$B72)/SUMIFS(Café_données!$C$3:$C$22,Café_données!$A$3:$A$22,Séries!$B$1,Café_données!$B$3:$B$22,$B72),0) -> 0.55559573 | G72: =IFERROR(SUMIFS(Café_données!$K$3:$K$22,Café_données!$A$3:$A$22,Séries!$B$1,Café_données!$B$3:$B$22,$B72)/SUMIFS(Café_données!$C$3:$C$22,Café_données!$A$3:$A$22,Séries!$B$1,Café_données!$B$3:$B$22,$B72),0) -> 0.84854108 | H72: =IF(SUMIFS(Café_données!$C$3:$C$22,Café_données!$T$3:$T$22,Séries!$B$3-1,Café_données!$B$3:$B$22,$B72)<Paramètres!$B$7,"–",SUMIFS(Café_données!$P$3:$P$22,Café_données!$T$3:$T$22,Séries!$B$3,Café_données!$B$3:$B$22,$B72)/SUMIFS(Café_données!$C$3:$C$22,Café_données!$T$3:$T$22,Séries!$B$3-1,Café_données!$B$3:$B$22,$B72)) -> 0.99650227
B73: COOKURU | C73: =SUMIFS(Café_données!$C$3:$C$22,Café_données!$A$3:$A$22,Séries!$B$1,Café_données!$B$3:$B$22,$B73) -> 1602 | D73: =IFERROR(SUMIFS(Café_données!$D$3:$D$22,Café_données!$A$3:$A$22,Séries!$B$1,Café_données!$B$3:$B$22,$B73)/SUMIFS(Café_données!$C$3:$C$22,Café_données!$A$3:$A$22,Séries!$B$1,Café_données!$B$3:$B$22,$B73),0) -> 0.37952559 | E73: =IFERROR(SUMIFS(Café_données!$E$3:$E$22,Café_données!$A$3:$A$22,Séries!$B$1,Café_données!$B$3:$B$22,$B73)/SUMIFS(Café_données!$C$3:$C$22,Café_données!$A$3:$A$22,Séries!$B$1,Café_données!$B$3:$B$22,$B73),0) -> 0.50062422 | F73: =IFERROR(SUMIFS(Café_données!$G$3:$G$22,Café_données!$A$3:$A$22,Séries!$B$1,Café_données!$B$3:$B$22,$B73)/SUMIFS(Café_données!$C$3:$C$22,Café_données!$A$3:$A$22,Séries!$B$1,Café_données!$B$3:$B$22,$B73),0) -> 0.54400125 | G73: =IFERROR(SUMIFS(Café_données!$K$3:$K$22,Café_données!$A$3:$A$22,Séries!$B$1,Café_données!$B$3:$B$22,$B73)/SUMIFS(Café_données!$C$3:$C$22,Café_données!$A$3:$A$22,Séries!$B$1,Café_données!$B$3:$B$22,$B73),0) -> 0 | H73: =IF(SUMIFS(Café_données!$C$3:$C$22,Café_données!$T$3:$T$22,Séries!$B$3-1,Café_données!$B$3:$B$22,$B73)<Paramètres!$B$7,"–",SUMIFS(Café_données!$P$3:$P$22,Café_données!$T$3:$T$22,Séries!$B$3,Café_données!$B$3:$B$22,$B73)/SUMIFS(Café_données!$C$3:$C$22,Café_données!$T$3:$T$22,Séries!$B$3-1,Café_données!$B$3:$B$22,$B73)) -> –
B74: COOPADE | C74: =SUMIFS(Café_données!$C$3:$C$22,Café_données!$A$3:$A$22,Séries!$B$1,Café_données!$B$3:$B$22,$B74) -> 7871 | D74: =IFERROR(SUMIFS(Café_données!$D$3:$D$22,Café_données!$A$3:$A$22,Séries!$B$1,Café_données!$B$3:$B$22,$B74)/SUMIFS(Café_données!$C$3:$C$22,Café_données!$A$3:$A$22,Séries!$B$1,Café_données!$B$3:$B$22,$B74),0) -> 0.25765468 | E74: =IFERROR(SUMIFS(Café_données!$E$3:$E$22,Café_données!$A$3:$A$22,Séries!$B$1,Café_données!$B$3:$B$22,$B74)/SUMIFS(Café_données!$C$3:$C$22,Café_données!$A$3:$A$22,Séries!$B$1,Café_données!$B$3:$B$22,$B74),0) -> 0.49231356 | F74: =IFERROR(SUMIFS(Café_données!$G$3:$G$22,Café_données!$A$3:$A$22,Séries!$B$1,Café_données!$B$3:$B$22,$B74)/SUMIFS(Café_données!$C$3:$C$22,Café_données!$A$3:$A$22,Séries!$B$1,Café_données!$B$3:$B$22,$B74),0) -> 0.55743108 | G74: =IFERROR(SUMIFS(Café_données!$K$3:$K$22,Café_données!$A$3:$A$22,Séries!$B$1,Café_données!$B$3:$B$22,$B74)/SUMIFS(Café_données!$C$3:$C$22,Café_données!$A$3:$A$22,Séries!$B$1,Café_données!$B$3:$B$22,$B74),0) -> 0.5407191 | H74: =IF(SUMIFS(Café_données!$C$3:$C$22,Café_données!$T$3:$T$22,Séries!$B$3-1,Café_données!$B$3:$B$22,$B74)<Paramètres!$B$7,"–",SUMIFS(Café_données!$P$3:$P$22,Café_données!$T$3:$T$22,Séries!$B$3,Café_données!$B$3:$B$22,$B74)/SUMIFS(Café_données!$C$3:$C$22,Café_données!$T$3:$T$22,Séries!$B$3-1,Café_données!$B$3:$B$22,$B74)) -> 0.99709686
B75: Ensemble | C75: =SUMIFS(Café_données!$C$3:$C$22,Café_données!$A$3:$A$22,Séries!$B$1,Café_données!$B$3:$B$22,"*") -> 42433 | D75: =IFERROR(SUMIFS(Café_données!$D$3:$D$22,Café_données!$A$3:$A$22,Séries!$B$1,Café_données!$B$3:$B$22,"*")/SUMIFS(Café_données!$C$3:$C$22,Café_données!$A$3:$A$22,Séries!$B$1,Café_données!$B$3:$B$22,"*"),0) -> 0.22694601 | E75: =IFERROR(SUMIFS(Café_données!$E$3:$E$22,Café_données!$A$3:$A$22,Séries!$B$1,Café_données!$B$3:$B$22,"*")/SUMIFS(Café_données!$C$3:$C$22,Café_données!$A$3:$A$22,Séries!$B$1,Café_données!$B$3:$B$22,"*"),0) -> 0.44884877 | F75: =IFERROR(SUMIFS(Café_données!$G$3:$G$22,Café_données!$A$3:$A$22,Séries!$B$1,Café_données!$B$3:$B$22,"*")/SUMIFS(Café_données!$C$3:$C$22,Café_données!$A$3:$A$22,Séries!$B$1,Café_données!$B$3:$B$22,"*"),0) -> 0.55500436 | G75: =IFERROR(SUMIFS(Café_données!$K$3:$K$22,Café_données!$A$3:$A$22,Séries!$B$1,Café_données!$B$3:$B$22,"*")/SUMIFS(Café_données!$C$3:$C$22,Café_données!$A$3:$A$22,Séries!$B$1,Café_données!$B$3:$B$22,"*"),0) -> 0.71458535 | H75: =IF(SUMIFS(Café_données!$C$3:$C$22,Café_données!$T$3:$T$22,Séries!$B$3-1,Café_données!$B$3:$B$22,"*")<Paramètres!$B$7,"–",SUMIFS(Café_données!$P$3:$P$22,Café_données!$T$3:$T$22,Séries!$B$3,Café_données!$B$3:$B$22,"*")/SUMIFS(Café_données!$C$3:$C$22,Café_données!$T$3:$T$22,Séries!$B$3-1,Café_données!$B$3:$B$22,"*")) -> 0.99592537
B76: En rouge : femmes sous 15 % ou jeunes sous 30 %. Rétention = producteurs de N-1 présents en N, sur la dernière campagne sélectionnée ; « – » pour une OP nouvelle.
B78: Messages clés et avertissement
B79: 1. Couverture : 12 184 producteurs café en 2025 (×3,2 depuis 2019), 25,6 % de femmes et 44,7 % de jeunes ; la hausse vient surtout de COOPADE et COOKURU (+68 % pour CKK et COOKKANZ).
B80: 2. Revenu cacao : revenu net médian de 3 301 USD/an ; 59 % des ménages dépassent le seuil de référence, 40 % seulement une fois le seuil ajusté à la taille des ménages (10,3 personnes).
B81: 3. Vulnérabilité : 87 % du revenu vient du cacao et 80 % des ménages vivent avec moins de 2,15 USD par personne et par jour.
B82: 4. Données : production, CA et marge café sont calculés par paramètres fixes et ne mesurent pas l'impact. Collecter les ventes réelles par producteur est la priorité.
B84: Sources : base consolidée Rikolto café 2019-2025 (42 433 lignes) ; enquête Living Income Cacao Okapi (88 ménages, mars 2024) ; Anker Research Institute (2025) ; Banque mondiale.

Sheet Séries
A1: Critère campagne | B1: =IF(Dashboard!$C$4="Toutes","*",TEXT(Dashboard!$C$4,"0")) -> *
A2: Critère coopérative | B2: =IF(Dashboard!$C$5="Toutes","*",Dashboard!$C$5) -> *
A3: Dernière campagne sélectionnée | B3: =IF(Dashboard!$C$4="Toutes",MAX(Café_données!$T$3:$T$22),VALUE(Dashboard!$C$4)) -> 2025
A5: Café par campagne (suit le filtre Coopérative) | L5: Composition du revenu net (88 ménages)
A6: Campagne | B6: Producteurs | C6: CKK + COOKKANZ | D6: COOPADE + COOKURU | E6: Femmes | F6: Jeunes 15-35 | G6: Superficie (ha) | H6: Production estimée (t) | I6: Marge estimée / producteur | J6: Rétention vs N-1 | L6: Source | M6: Part du revenu net
A7: 2019 | B7: =SUMIFS(Café_données!$C$3:$C$22,Café_données!$A$3:$A$22,$A7,Café_données!$B$3:$B$22,Séries!$B$2) -> 3864 | C7: =SUMIFS(Café_données!$C$3:$C$22,Café_données!$A$3:$A$22,$A7,Café_données!$B$3:$B$22,"CKK")+SUMIFS(Café_données!$C$3:$C$22,Café_données!$A$3:$A$22,$A7,Café_données!$B$3:$B$22,"COOKKANZ") -> 3864 | D7: =SUMIFS(Café_données!$C$3:$C$22,Café_données!$A$3:$A$22,$A7,Café_données!$B$3:$B$22,"COOPADE")+SUMIFS(Café_données!$C$3:$C$22,Café_données!$A$3:$A$22,$A7,Café_données!$B$3:$B$22,"COOKURU") -> 0 | E7: =IFERROR(SUMIFS(Café_données!$D$3:$D$22,Café_données!$A$3:$A$22,$A7,Café_données!$B$3:$B$22,Séries!$B$2)/SUMIFS(Café_données!$C$3:$C$22,Café_données!$A$3:$A$22,$A7,Café_données!$B$3:$B$22,Séries!$B$2),NA()) -> 0.21609731 | F7: =IFERROR(SUMIFS(Café_données!$E$3:$E$22,Café_données!$A$3:$A$22,$A7,Café_données!$B$3:$B$22,Séries!$B$2)/SUMIFS(Café_données!$C$3:$C$22,Café_données!$A$3:$A$22,$A7,Café_données!$B$3:$B$22,Séries!$B$2),NA()) -> 0.60766046 | G7: =SUMIFS(Café_données!$G$3:$G$22,Café_données!$A$3:$A$22,$A7,Café_données!$B$3:$B$22,Séries!$B$2) -> 2158.32 | H7: =SUMIFS(Café_données!$H$3:$H$22,Café_données!$A$3:$A$22,$A7,Café_données!$B$3:$B$22,Séries!$B$2) -> 3237.47 | I7: =IFERROR(SUMIFS(Café_données!$J$3:$J$22,Café_données!$A$3:$A$22,$A7,Café_données!$B$3:$B$22,Séries!$B$2)/SUMIFS(Café_données!$C$3:$C$22,Café_données!$A$3:$A$22,$A7,Café_données!$B$3:$B$22,Séries!$B$2),NA()) -> 276.49198 | J7: =IF(SUMIFS(Café_données!$C$3:$C$22,Café_données!$T$3:$T$22,VALUE($A7)-1,Café_données!$B$3:$B$22,Séries!$B$2)<Paramètres!$B$7,"–",SUMIFS(Café_données!$P$3:$P$22,Café_données!$A$3:$A$22,$A7,Café_données!$B$3:$B$22,Séries!$B$2)/SUMIFS(Café_données!$C$3:$C$22,Café_données!$T$3:$T$22,VALUE($A7)-1,Café_données!$B$3:$B$22,Séries!$B$2)) -> – | L7: Autres cultures vivrières | M7: =SUM(Cacao_ménages!$Q$3:$Q$90)/SUM(Cacao_ménages!$H$3:$H$90) -> -0.0071226214
A8: 2020 | B8: =SUMIFS(Café_données!$C$3:$C$22,Café_données!$A$3:$A$22,$A8,Café_données!$B$3:$B$22,Séries!$B$2) -> 4170 | C8: =SUMIFS(Café_données!$C$3:$C$22,Café_données!$A$3:$A$22,$A8,Café_données!$B$3:$B$22,"CKK")+SUMIFS(Café_données!$C$3:$C$22,Café_données!$A$3:$A$22,$A8,Café_données!$B$3:$B$22,"COOKKANZ") -> 4170 | D8: =SUMIFS(Café_données!$C$3:$C$22,Café_données!$A$3:$A$22,$A8,Café_données!$B$3:$B$22,"COOPADE")+SUMIFS(Café_données!$C$3:$C$22,Café_données!$A$3:$A$22,$A8,Café_données!$B$3:$B$22,"COOKURU") -> 0 | E8: =IFERROR(SUMIFS(Café_données!$D$3:$D$22,Café_données!$A$3:$A$22,$A8,Café_données!$B$3:$B$22,Séries!$B$2)/SUMIFS(Café_données!$C$3:$C$22,Café_données!$A$3:$A$22,$A8,Café_données!$B$3:$B$22,Séries!$B$2),NA()) -> 0.20767386 | F8: =IFERROR(SUMIFS(Café_données!$E$3:$E$22,Café_données!$A$3:$A$22,$A8,Café_données!$B$3:$B$22,Séries!$B$2)/SUMIFS(Café_données!$C$3:$C$22,Café_données!$A$3:$A$22,$A8,Café_données!$B$3:$B$22,Séries!$B$2),NA()) -> 0.57673861 | G8: =SUMIFS(Café_données!$G$3:$G$22,Café_données!$A$3:$A$22,$A8,Café_données!$B$3:$B$22,Séries!$B$2) -> 2308.84 | H8: =SUMIFS(Café_données!$H$3:$H$22,Café_données!$A$3:$A$22,$A8,Café_données!$B$3:$B$22,Séries!$B$2) -> 3925.04 | I8: =IFERROR(SUMIFS(Café_données!$J$3:$J$22,Café_données!$A$3:$A$22,$A8,Café_données!$B$3:$B$22,Séries!$B$2)/SUMIFS(Café_données!$C$3:$C$22,Café_données!$A$3:$A$22,$A8,Café_données!$B$3:$B$22,Séries!$B$2),NA()) -> 310.61463 | J8: =IF(SUMIFS(Café_données!$C$3:$C$22,Café_données!$T$3:$T$22,VALUE($A8)-1,Café_données!$B$3:$B$22,Séries!$B$2)<Paramètres!$B$7,"–",SUMIFS(Café_données!$P$3:$P$22,Café_données!$A$3:$A$22,$A8,Café_données!$B$3:$B$22,Séries!$B$2)/SUMIFS(Café_données!$C$3:$C$22,Café_données!$T$3:$T$22,VALUE($A8)-1,Café_données!$B$3:$B$22,Séries!$B$2)) -> 0.86231884 | L8: Café | M8: =SUM(Cacao_ménages!$O$3:$O$90)/SUM(Cacao_ménages!$H$3:$H$90) -> 0.0037505001
A9: 2021 | B9: =SUMIFS(Café_données!$C$3:$C$22,Café_données!$A$3:$A$22,$A9,Café_données!$B$3:$B$22,Séries!$B$2) -> 4065 | C9: =SUMIFS(Café_données!$C$3:$C$22,Café_données!$A$3:$A$22,$A9,Café_données!$B$3:$B$22,"CKK")+SUMIFS(Café_données!$C$3:$C$22,Café_données!$A$3:$A$22,$A9,Café_données!$B$3:$B$22,"COOKKANZ") -> 4065 | D9: =SUMIFS(Café_données!$C$3:$C$22,Café_données!$A$3:$A$22,$A9,Café_données!$B$3:$B$22,"COOPADE")+SUMIFS(Café_données!$C$3:$C$22,Café_données!$A$3:$A$22,$A9,Café_données!$B$3:$B$22,"COOKURU") -> 0 | E9: =IFERROR(SUMIFS(Café_données!$D$3:$D$22,Café_données!$A$3:$A$22,$A9,Café_données!$B$3:$B$22,Séries!$B$2)/SUMIFS(Café_données!$C$3:$C$22,Café_données!$A$3:$A$22,$A9,Café_données!$B$3:$B$22,Séries!$B$2),NA()) -> 0.20762608 | F9: =IFERROR(SUMIFS(Café_données!$E$3:$E$22,Café_données!$A$3:$A$22,$A9,Café_données!$B$3:$B$22,Séries!$B$2)/SUMIFS(Café_données!$C$3:$C$22,Café_données!$A$3:$A$22,$A9,Café_données!$B$3:$B$22,Séries!$B$2),NA()) -> 0.51537515 | G9: =SUMIFS(Café_données!$G$3:$G$22,Café_données!$A$3:$A$22,$A9,Café_données!$B$3:$B$22,Séries!$B$2) -> 2250.46 | H9: =SUMIFS(Café_données!$H$3:$H$22,Café_données!$A$3:$A$22,$A9,Café_données!$B$3:$B$22,Séries!$B$2) -> 7876.59 | I9: =IFERROR(SUMIFS(Café_données!$J$3:$J$22,Café_données!$A$3:$A$22,$A9,Café_données!$B$3:$B$22,Séries!$B$2)/SUMIFS(Café_données!$C$3:$C$22,Café_données!$A$3:$A$22,$A9,Café_données!$B$3:$B$22,Séries!$B$2),NA()) -> 639.42804 | J9: =IF(SUMIFS(Café_données!$C$3:$C$22,Café_données!$T$3:$T$22,VALUE($A9)-1,Café_données!$B$3:$B$22,Séries!$B$2)<Paramètres!$B$7,"–",SUMIFS(Café_données!$P$3:$P$22,Café_données!$A$3:$A$22,$A9,Café_données!$B$3:$B$22,Séries!$B$2)/SUMIFS(Café_données!$C$3:$C$22,Café_données!$T$3:$T$22,VALUE($A9)-1,Café_données!$B$3:$B$22,Séries!$B$2)) -> 0.94556355 | L9: Élevage | M9: =SUM(Cacao_ménages!$R$3:$R$90)/SUM(Cacao_ménages!$H$3:$H$90) -> 0.010490304
A10: 2022 | B10: =SUMIFS(Café_données!$C$3:$C$22,Café_données!$A$3:$A$22,$A10,Café_données!$B$3:$B$22,Séries!$B$2) -> 4295 | C10: =SUMIFS(Café_données!$C$3:$C$22,Café_données!$A$3:$A$22,$A10,Café_données!$B$3:$B$22,"CKK")+SUMIFS(Café_données!$C$3:$C$22,Café_données!$A$3:$A$22,$A10,Café_données!$B$3:$B$22,"COOKKANZ") -> 4294 | D10: =SUMIFS(Café_données!$C$3:$C$22,Café_données!$A$3:$A$22,$A10,Café_données!$B$3:$B$22,"COOPADE")+SUMIFS(Café_données!$C$3:$C$22,Café_données!$A$3:$A$22,$A10,Café_données!$B$3:$B$22,"COOKURU") -> 1 | E10: =IFERROR(SUMIFS(Café_données!$D$3:$D$22,Café_données!$A$3:$A$22,$A10,Café_données!$B$3:$B$22,Séries!$B$2)/SUMIFS(Café_données!$C$3:$C$22,Café_données!$A$3:$A$22,$A10,Café_données!$B$3:$B$22,Séries!$B$2),NA()) -> 0.20582072 | F10: =IFERROR(SUMIFS(Café_données!$E$3:$E$22,Café_données!$A$3:$A$22,$A10,Café_données!$B$3:$B$22,Séries!$B$2)/SUMIFS(Café_données!$C$3:$C$22,Café_données!$A$3:$A$22,$A10,Café_données!$B$3:$B$22,Séries!$B$2),NA()) -> 0.43329453 | G10: =SUMIFS(Café_données!$G$3:$G$22,Café_données!$A$3:$A$22,$A10,Café_données!$B$3:$B$22,Séries!$B$2) -> 2395.25 | H10: =SUMIFS(Café_données!$H$3:$H$22,Café_données!$A$3:$A$22,$A10,Café_données!$B$3:$B$22,Séries!$B$2) -> 8756.79 | I10: =IFERROR(SUMIFS(Café_données!$J$3:$J$22,Café_données!$A$3:$A$22,$A10,Café_données!$B$3:$B$22,Séries!$B$2)/SUMIFS(Café_données!$C$3:$C$22,Café_données!$A$3:$A$22,$A10,Café_données!$B$3:$B$22,Séries!$B$2),NA()) -> 672.81513 | J10: =IF(SUMIFS(Café_données!$C$3:$C$22,Café_données!$T$3:$T$22,VALUE($A10)-1,Café_données!$B$3:$B$22,Séries!$B$2)<Paramètres!$B$7,"–",SUMIFS(Café_données!$P$3:$P$22,Café_données!$A$3:$A$22,$A10,Café_données!$B$3:$B$22,Séries!$B$2)/SUMIFS(Café_données!$C$3:$C$22,Café_données!$T$3:$T$22,VALUE($A10)-1,Café_données!$B$3:$B$22,Séries!$B$2)) -> 0.9899139 | L10: Transferts et autres | M10: =SUM(Cacao_ménages!$T$3:$T$90)/SUM(Cacao_ménages!$H$3:$H$90) -> 0.012942554
A11: 2023 | B11: =SUMIFS(Café_données!$C$3:$C$22,Café_données!$A$3:$A$22,$A11,Café_données!$B$3:$B$22,Séries!$B$2) -> 4529 | C11: =SUMIFS(Café_données!$C$3:$C$22,Café_données!$A$3:$A$22,$A11,Café_données!$B$3:$B$22,"CKK")+SUMIFS(Café_données!$C$3:$C$22,Café_données!$A$3:$A$22,$A11,Café_données!$B$3:$B$22,"COOKKANZ") -> 4525 | D11: =SUMIFS(Café_données!$C$3:$C$22,Café_données!$A$3:$A$22,$A11,Café_données!$B$3:$B$22,"COOPADE")+SUMIFS(Café_données!$C$3:$C$22,Café_données!$A$3:$A$22,$A11,Café_données!$B$3:$B$22,"COOKURU") -> 4 | E11: =IFERROR(SUMIFS(Café_données!$D$3:$D$22,Café_données!$A$3:$A$22,$A11,Café_données!$B$3:$B$22,Séries!$B$2)/SUMIFS(Café_données!$C$3:$C$22,Café_données!$A$3:$A$22,$A11,Café_données!$B$3:$B$22,Séries!$B$2),NA()) -> 0.20865533 | F11: =IFERROR(SUMIFS(Café_données!$E$3:$E$22,Café_données!$A$3:$A$22,$A11,Café_données!$B$3:$B$22,Séries!$B$2)/SUMIFS(Café_données!$C$3:$C$22,Café_données!$A$3:$A$22,$A11,Café_données!$B$3:$B$22,Séries!$B$2),NA()) -> 0.32391256 | G11: =SUMIFS(Café_données!$G$3:$G$22,Café_données!$A$3:$A$22,$A11,Café_données!$B$3:$B$22,Séries!$B$2) -> 2510 | H11: =SUMIFS(Café_données!$H$3:$H$22,Café_données!$A$3:$A$22,$A11,Café_données!$B$3:$B$22,Séries!$B$2) -> 10077.51 | I11: =IFERROR(SUMIFS(Café_données!$J$3:$J$22,Café_données!$A$3:$A$22,$A11,Café_données!$B$3:$B$22,Séries!$B$2)/SUMIFS(Café_données!$C$3:$C$22,Café_données!$A$3:$A$22,$A11,Café_données!$B$3:$B$22,Séries!$B$2),NA()) -> 734.28527 | J11: =IF(SUMIFS(Café_données!$C$3:$C$22,Café_données!$T$3:$T$22,VALUE($A11)-1,Café_données!$B$3:$B$22,Séries!$B$2)<Paramètres!$B$7,"–",SUMIFS(Café_données!$P$3:$P$22,Café_données!$A$3:$A$22,$A11,Café_données!$B$3:$B$22,Séries!$B$2)/SUMIFS(Café_données!$C$3:$C$22,Café_données!$T$3:$T$22,VALUE($A11)-1,Café_données!$B$3:$B$22,Séries!$B$2)) -> 0.96484284 | L11: Activités hors ferme | M11: =SUM(Cacao_ménages!$S$3:$S$90)/SUM(Cacao_ménages!$H$3:$H$90) -> 0.045161348
A12: 2024 | B12: =SUMIFS(Café_données!$C$3:$C$22,Café_données!$A$3:$A$22,$A12,Café_données!$B$3:$B$22,Séries!$B$2) -> 9326 | C12: =SUMIFS(Café_données!$C$3:$C$22,Café_données!$A$3:$A$22,$A12,Café_données!$B$3:$B$22,"CKK")+SUMIFS(Café_données!$C$3:$C$22,Café_données!$A$3:$A$22,$A12,Café_données!$B$3:$B$22,"COOKKANZ") -> 5536 | D12: =SUMIFS(Café_données!$C$3:$C$22,Café_données!$A$3:$A$22,$A12,Café_données!$B$3:$B$22,"COOPADE")+SUMIFS(Café_données!$C$3:$C$22,Café_données!$A$3:$A$22,$A12,Café_données!$B$3:$B$22,"COOKURU") -> 3790 | E12: =IFERROR(SUMIFS(Café_données!$D$3:$D$22,Café_données!$A$3:$A$22,$A12,Café_données!$B$3:$B$22,Séries!$B$2)/SUMIFS(Café_données!$C$3:$C$22,Café_données!$A$3:$A$22,$A12,Café_données!$B$3:$B$22,Séries!$B$2),NA()) -> 0.22882265 | F12: =IFERROR(SUMIFS(Café_données!$E$3:$E$22,Café_données!$A$3:$A$22,$A12,Café_données!$B$3:$B$22,Séries!$B$2)/SUMIFS(Café_données!$C$3:$C$22,Café_données!$A$3:$A$22,$A12,Café_données!$B$3:$B$22,Séries!$B$2),NA()) -> 0.36703839 | G12: =SUMIFS(Café_données!$G$3:$G$22,Café_données!$A$3:$A$22,$A12,Café_données!$B$3:$B$22,Séries!$B$2) -> 5157.24 | H12: =SUMIFS(Café_données!$H$3:$H$22,Café_données!$A$3:$A$22,$A12,Café_données!$B$3:$B$22,Séries!$B$2) -> 20757.93 | I12: =IFERROR(SUMIFS(Café_données!$J$3:$J$22,Café_données!$A$3:$A$22,$A12,Café_données!$B$3:$B$22,Séries!$B$2)/SUMIFS(Café_données!$C$3:$C$22,Café_données!$A$3:$A$22,$A12,Café_données!$B$3:$B$22,Séries!$B$2),NA()) -> 734.51823 | J12: =IF(SUMIFS(Café_données!$C$3:$C$22,Café_données!$T$3:$T$22,VALUE($A12)-1,Café_données!$B$3:$B$22,Séries!$B$2)<Paramètres!$B$7,"–",SUMIFS(Café_données!$P$3:$P$22,Café_données!$A$3:$A$22,$A12,Café_données!$B$3:$B$22,Séries!$B$2)/SUMIFS(Café_données!$C$3:$C$22,Café_données!$T$3:$T$22,VALUE($A12)-1,Café_données!$B$3:$B$22,Séries!$B$2)) -> 0.97240009 | L12: Agroforesterie | M12: =SUM(Cacao_ménages!$P$3:$P$90)/SUM(Cacao_ménages!$H$3:$H$90) -> 0.068705168
A13: 2025 | B13: =SUMIFS(Café_données!$C$3:$C$22,Café_données!$A$3:$A$22,$A13,Café_données!$B$3:$B$22,Séries!$B$2) -> 12184 | C13: =SUMIFS(Café_données!$C$3:$C$22,Café_données!$A$3:$A$22,$A13,Café_données!$B$3:$B$22,"CKK")+SUMIFS(Café_données!$C$3:$C$22,Café_données!$A$3:$A$22,$A13,Café_données!$B$3:$B$22,"COOKKANZ") -> 6506 | D13: =SUMIFS(Café_données!$C$3:$C$22,Café_données!$A$3:$A$22,$A13,Café_données!$B$3:$B$22,"COOPADE")+SUMIFS(Café_données!$C$3:$C$22,Café_données!$A$3:$A$22,$A13,Café_données!$B$3:$B$22,"COOKURU") -> 5678 | E13: =IFERROR(SUMIFS(Café_données!$D$3:$D$22,Café_données!$A$3:$A$22,$A13,Café_données!$B$3:$B$22,Séries!$B$2)/SUMIFS(Café_données!$C$3:$C$22,Café_données!$A$3:$A$22,$A13,Café_données!$B$3:$B$22,Séries!$B$2),NA()) -> 0.25623769 | F13: =IFERROR(SUMIFS(Café_données!$E$3:$E$22,Café_données!$A$3:$A$22,$A13,Café_données!$B$3:$B$22,Séries!$B$2)/SUMIFS(Café_données!$C$3:$C$22,Café_données!$A$3:$A$22,$A13,Café_données!$B$3:$B$22,Séries!$B$2),NA()) -> 0.44706172 | G13: =SUMIFS(Café_données!$G$3:$G$22,Café_données!$A$3:$A$22,$A13,Café_données!$B$3:$B$22,Séries!$B$2) -> 6770.39 | H13: =SUMIFS(Café_données!$H$3:$H$22,Café_données!$A$3:$A$22,$A13,Café_données!$B$3:$B$22,Séries!$B$2) -> 26432.49 | I13: =IFERROR(SUMIFS(Café_données!$J$3:$J$22,Café_données!$A$3:$A$22,$A13,Café_données!$B$3:$B$22,Séries!$B$2)/SUMIFS(Café_données!$C$3:$C$22,Café_données!$A$3:$A$22,$A13,Café_données!$B$3:$B$22,Séries!$B$2),NA()) -> 715.91612 | J13: =IF(SUMIFS(Café_données!$C$3:$C$22,Café_données!$T$3:$T$22,VALUE($A13)-1,Café_données!$B$3:$B$22,Séries!$B$2)<Paramètres!$B$7,"–",SUMIFS(Café_données!$P$3:$P$22,Café_données!$A$3:$A$22,$A13,Café_données!$B$3:$B$22,Séries!$B$2)/SUMIFS(Café_données!$C$3:$C$22,Café_données!$T$3:$T$22,VALUE($A13)-1,Café_données!$B$3:$B$22,Séries!$B$2)) -> 0.99592537 | L13: Cacao | M13: =SUM(Cacao_ménages!$N$3:$N$90)/SUM(Cacao_ménages!$H$3:$H$90) -> 0.86607275
A16: Cacao par section
A17: Section | B17: Ménages | C17: Revenu net médian | D17: Seuil de référence | E17: Au-dessus seuil réf. | F17: Au-dessus seuil ajusté | G17: Taille moyenne | H17: Ha cacao médian | I17: Rendement médian (kg/ha) | J17: Prix médian (USD/kg)
A18: Babungwe | B18: =COUNTIF(Cacao_ménages!$B$3:$B$90,$A18) -> 22 | C18: {=MEDIAN(IF(Cacao_ménages!$B$3:$B$90=$A18,Cacao_ménages!$H$3:$H$90))} -> 2760 | D18: =Paramètres!$B$4 -> 2628 | E18: =AVERAGEIF(Cacao_ménages!$B$3:$B$90,$A18,Cacao_ménages!$J$3:$J$90) -> 0.5 | F18: =AVERAGEIF(Cacao_ménages!$B$3:$B$90,$A18,Cacao_ménages!$K$3:$K$90) -> 0.27272727 | G18: =AVERAGEIF(Cacao_ménages!$B$3:$B$90,$A18,Cacao_ménages!$D$3:$D$90) -> 8.8181818 | H18: {=MEDIAN(IF(Cacao_ménages!$B$3:$B$90=$A18,Cacao_ménages!$E$3:$E$90))} -> 3 | I18: {=MEDIAN(IF(Cacao_ménages!$B$3:$B$90=$A18,Cacao_ménages!$F$3:$F$90))} -> 485 | J18: {=MEDIAN(IF(Cacao_ménages!$B$3:$B$90=$A18,Cacao_ménages!$G$3:$G$90))} -> 3.625
A19: Mambasa | B19: =COUNTIF(Cacao_ménages!$B$3:$B$90,$A19) -> 22 | C19: {=MEDIAN(IF(Cacao_ménages!$B$3:$B$90=$A19,Cacao_ménages!$H$3:$H$90))} -> 2883 | D19: =Paramètres!$B$4 -> 2628 | E19: =AVERAGEIF(Cacao_ménages!$B$3:$B$90,$A19,Cacao_ménages!$J$3:$J$90) -> 0.59090909 | F19: =AVERAGEIF(Cacao_ménages!$B$3:$B$90,$A19,Cacao_ménages!$K$3:$K$90) -> 0.27272727 | G19: =AVERAGEIF(Cacao_ménages!$B$3:$B$90,$A19,Cacao_ménages!$D$3:$D$90) -> 12.636364 | H19: {=MEDIAN(IF(Cacao_ménages!$B$3:$B$90=$A19,Cacao_ménages!$E$3:$E$90))} -> 3 | I19: {=MEDIAN(IF(Cacao_ménages!$B$3:$B$90=$A19,Cacao_ménages!$F$3:$F$90))} -> 435 | J19: {=MEDIAN(IF(Cacao_ménages!$B$3:$B$90=$A19,Cacao_ménages!$G$3:$G$90))} -> 4.0325
A20: Mayuano | B20: =COUNTIF(Cacao_ménages!$B$3:$B$90,$A20) -> 21 | C20: {=MEDIAN(IF(Cacao_ménages!$B$3:$B$90=$A20,Cacao_ménages!$H$3:$H$90))} -> 4799 | D20: =Paramètres!$B$4 -> 2628 | E20: =AVERAGEIF(Cacao_ménages!$B$3:$B$90,$A20,Cacao_ménages!$J$3:$J$90) -> 0.76190476 | F20: =AVERAGEIF(Cacao_ménages!$B$3:$B$90,$A20,Cacao_ménages!$K$3:$K$90) -> 0.71428571 | G20: =AVERAGEIF(Cacao_ménages!$B$3:$B$90,$A20,Cacao_ménages!$D$3:$D$90) -> 7.7619048 | H20: {=MEDIAN(IF(Cacao_ménages!$B$3:$B$90=$A20,Cacao_ménages!$E$3:$E$90))} -> 4 | I20: {=MEDIAN(IF(Cacao_ménages!$B$3:$B$90=$A20,Cacao_ménages!$F$3:$F$90))} -> 875 | J20: {=MEDIAN(IF(Cacao_ménages!$B$3:$B$90=$A20,Cacao_ménages!$G$3:$G$90))} -> 2.057
A21: Mungamba | B21: =COUNTIF(Cacao_ménages!$B$3:$B$90,$A21) -> 23 | C21: {=MEDIAN(IF(Cacao_ménages!$B$3:$B$90=$A21,Cacao_ménages!$H$3:$H$90))} -> 3060 | D21: =Paramètres!$B$4 -> 2628 | E21: =AVERAGEIF(Cacao_ménages!$B$3:$B$90,$A21,Cacao_ménages!$J$3:$J$90) -> 0.52173913 | F21: =AVERAGEIF(Cacao_ménages!$B$3:$B$90,$A21,Cacao_ménages!$K$3:$K$90) -> 0.34782609 | G21: =AVERAGEIF(Cacao_ménages!$B$3:$B$90,$A21,Cacao_ménages!$D$3:$D$90) -> 11.913043 | H21: {=MEDIAN(IF(Cacao_ménages!$B$3:$B$90=$A21,Cacao_ménages!$E$3:$E$90))} -> 4 | I21: {=MEDIAN(IF(Cacao_ménages!$B$3:$B$90=$A21,Cacao_ménages!$F$3:$F$90))} -> 441.667 | J21: {=MEDIAN(IF(Cacao_ménages!$B$3:$B$90=$A21,Cacao_ménages!$G$3:$G$90))} -> 4.004
A22: Ensemble | B22: =COUNT(Cacao_ménages!$H$3:$H$90) -> 88 | C22: =MEDIAN(Cacao_ménages!$H$3:$H$90) -> 3300.5 | D22: =Paramètres!$B$4 -> 2628 | E22: =AVERAGE(Cacao_ménages!$J$3:$J$90) -> 0.59090909 | F22: =AVERAGE(Cacao_ménages!$K$3:$K$90) -> 0.39772727 | G22: =AVERAGE(Cacao_ménages!$D$3:$D$90) -> 10.329545 | H22: =MEDIAN(Cacao_ménages!$E$3:$E$90) -> 3 | I22: =MEDIAN(Cacao_ménages!$F$3:$F$90) -> 566.667 | J22: =MEDIAN(Cacao_ménages!$G$3:$G$90) -> 3.6955
A30: Personnes uniques (identifiant longitudinal)
A31: Campagne \ OP | B31: Toutes | C31: CKK | D31: COOKKANZ | E31: COOKURU | F31: COOPADE
A32: Toutes | B32: 12833 | C32: 3446 | D32: 3880 | E32: 1602 | F32: 4157
A33: 2019 | B33: 3864 | C33: 2248 | D33: 1616
A34: 2020 | B34: 4170 | C34: 2363 | D34: 1807
A35: 2021 | B35: 4065 | C35: 2258 | D35: 1807
A36: 2022 | B36: 4295 | C36: 2263 | D36: 2031 | E36: 1
A37: 2023 | B37: 4529 | C37: 2333 | D37: 2192 | E37: 4
A38: 2024 | B38: 9326 | C38: 2677 | D38: 2859 | E38: 1 | F38: 3789
A39: 2025 | B39: 12184 | C39: 3190 | D39: 3316 | E39: 1596 | F39: 4082

Sheet Café_données
A1: Base café agrégée par campagne et coopérative (source : fact_cafe_producteurs.csv, 42 433 lignes)
A2: Campagne | B2: Coopérative | C2: Producteurs (inscriptions) | D2: Femmes | E2: Jeunes 15-35 | F2: Âge connu | G2: Superficie (ha) | H2: Production estimée (t cerise) | I2: CA estimé (USD) | J2: Marge estimée (USD) | K2: Conforme | L2: En conversion | M2: Non conforme | N2: Non renseigné | O2: Nouveaux | P2: Présents en N-1 | Q2: Territoire renseigné | R2: Carte en doublon | S2: Personnes uniques | T2: Année (nombre)
A3: 2019 | B3: CKK | C3: 2248 | D3: 633 | E3: 1431 | F3: 2248 | G3: 1259.03 | H3: 1888.54 | I3: 1038699 | J3: 623219 | K3: 0 | L3: 0 | M3: 2248 | N3: 0 | O3: 2248 | P3: 0 | Q3: 2248 | R3: 58 | S3: 2248 | T3: =VALUE(A3) -> 2019
A4: 2019 | B4: COOKKANZ | C4: 1616 | D4: 202 | E4: 917 | F4: 1589 | G4: 899.29 | H4: 1348.93 | I4: 741911 | J4: 445146 | K4: 0 | L4: 0 | M4: 1616 | N4: 0 | O4: 1616 | P4: 0 | Q4: 1616 | R4: 197 | S4: 1616 | T4: =VALUE(A4) -> 2019
A5: 2020 | B5: CKK | C5: 2363 | D5: 656 | E5: 1391 | F5: 2363 | G5: 1296.77 | H5: 2204.52 | I5: 1212484 | J5: 727490 | K5: 2349 | L5: 0 | M5: 14 | N5: 0 | O5: 232 | P5: 2131 | Q5: 2059 | R5: 146 | S5: 2363 | T5: =VALUE(A5) -> 2020
A6: 2020 | B6: COOKKANZ | C6: 1807 | D6: 210 | E6: 1014 | F6: 1807 | G6: 1012.07 | H6: 1720.52 | I6: 946288 | J6: 567773 | K6: 1807 | L6: 0 | M6: 0 | N6: 0 | O6: 606 | P6: 1201 | Q6: 1807 | R6: 0 | S6: 1807 | T6: =VALUE(A6) -> 2020
A7: 2021 | B7: CKK | C7: 2258 | D7: 634 | E7: 1181 | F7: 2258 | G7: 1249.67 | H7: 4373.84 | I7: 2405612 | J7: 1443367 | K7: 2258 | L7: 0 | M7: 0 | N7: 0 | O7: 2 | P7: 2136 | Q7: 2258 | R7: 58 | S7: 2258 | T7: =VALUE(A7) -> 2021
A8: 2021 | B8: COOKKANZ | C8: 1807 | D8: 210 | E8: 914 | F8: 1807 | G8: 1000.79 | H8: 3502.75 | I8: 1926514 | J8: 1155908 | K8: 1807 | L8: 0 | M8: 0 | N8: 0 | O8: 0 | P8: 1807 | Q8: 28 | R8: 0 | S8: 1807 | T8: =VALUE(A8) -> 2021
A9: 2022 | B9: CKK | C9: 2263 | D9: 633 | E9: 1011 | F9: 2263 | G9: 1255.09 | H9: 4583.62 | I9: 2520990 | J9: 1512594 | K9: 27 | L9: 0 | M9: 0 | N9: 2236 | O9: 1 | P9: 2256 | Q9: 54 | R9: 56 | S9: 2263 | T9: =VALUE(A9) -> 2022
A10: 2022 | B10: COOKKANZ | C10: 2031 | D10: 250 | E10: 850 | F10: 2023 | G10: 1139.69 | H10: 4171.27 | I10: 2294198 | J10: 1376519 | K10: 2016 | L10: 0 | M10: 0 | N10: 15 | O10: 247 | P10: 1768 | Q10: 34 | R10: 8 | S10: 2031 | T10: =VALUE(A10) -> 2022
A11: 2022 | B11: COOKURU | C11: 1 | D11: 1 | E11: 0 | F11: 1 | G11: 0.47 | H11: 1.9 | I11: 1047 | J11: 628 | K11: 0 | L11: 1 | M11: 0 | N11: 0 | O11: 1 | P11: 0 | Q11: 1 | R11: 0 | S11: 1 | T11: =VALUE(A11) -> 2022
A12: 2023 | B12: CKK | C12: 2333 | D12: 649 | E12: 786 | F12: 2333 | G12: 1300.11 | H12: 5219.74 | I12: 2870858 | J12: 1722515 | K12: 2319 | L12: 0 | M12: 14 | N12: 0 | O12: 0 | P12: 2113 | Q12: 2028 | R12: 144 | S12: 2333 | T12: =VALUE(A12) -> 2023
A13: 2023 | B13: COOKKANZ | C13: 2192 | D13: 294 | E13: 679 | F13: 2176 | G13: 1208 | H13: 4850.12 | I13: 2667566 | J13: 1600539 | K13: 2154 | L13: 23 | M13: 0 | N13: 15 | O13: 158 | P13: 2031 | Q13: 37 | R13: 8 | S13: 2192 | T13: =VALUE(A13) -> 2023
A14: 2023 | B14: COOKURU | C14: 4 | D14: 2 | E14: 2 | F14: 4 | G14: 1.89 | H14: 7.65 | I14: 4207 | J14: 2524 | K14: 0 | L14: 4 | M14: 0 | N14: 0 | O14: 4 | P14: 0 | Q14: 4 | R14: 0 | S14: 4 | T14: =VALUE(A14) -> 2023
... A22: 2025 | B22: COOPADE | C22: 4082 | D22: 1083 | E22: 2031 | F22: 4058 | G22: 2291.97 | H22: 8294.9 | I22: 4562197 | J22: 2737318 | K22: 4082 | L22: 0 | M22: 0 | N22: 0 | O22: 304 | P22: 3778 | Q22: 3209 | R22: 728 | S22: 4082 | T22: =VALUE(A22) -> 2025

Sheet Cacao_ménages
A1: Enquête Living Income Cacao Okapi, mars 2024 : 88 ménages valides (source : fact_cacao_menages.csv)
A2: ID ménage | B2: Section | C2: Sexe du chef | D2: Taille du ménage | E2: Superficie cacao (ha) | F2: Rendement (kg/ha) | G2: Prix (USD/kg) | H2: Revenu net total (USD/an) | I2: Seuil ajusté à la taille (USD/an) | J2: Atteint seuil réf. (1/0) | K2: Atteint seuil ajusté (1/0) | L2: Revenu / pers. / jour (USD) | M2: Solde revenu − dépenses (USD) | N2: Revenu cacao | O2: Revenu café | P2: Agroforesterie | Q2: Autres cultures vivrières | R2: Élevage | S2: Activités hors ferme | T2: Transferts et autres | U2: Valeur extrême (1/0)
A3: 1 | B3: Babungwe | C3: Homme | D3: 13 | E3: 4 | F3: 300 | G3: 3.559 | H3: 4565 | I3: 5694 | J3: 1 | K3: 0 | L3: 0.962 | M3: 1365 | N3: 3640 | O3: 0 | P3: 825 | Q3: 100 | R3: 0 | S3: 0 | T3: 0 | U3: 0
A4: 2 | B4: Babungwe | C4: Homme | D4: 10 | E4: 2 | F4: 400 | G4: 4 | H4: 1692 | I4: 4380 | J4: 0 | K4: 0 | L4: 0.464 | M4: 437 | N4: 2198 | O4: 0 | P4: -456 | Q4: -50 | R4: 0 | S4: 0 | T4: 0 | U4: 0
A5: 3 | B5: Babungwe | C5: Homme | D5: 6 | E5: 3 | F5: 520 | G5: 3.64 | H5: 1360 | I5: 2628 | J5: 0 | K5: 0 | L5: 0.621 | M5: 320 | N5: 1410 | O5: 0 | P5: 0 | Q5: -50 | R5: 0 | S5: 0 | T5: 0 | U5: 0
A6: 4 | B6: Babungwe | C6: Homme | D6: 10 | E6: 6 | F6: 425 | G6: 3.719 | H6: 6543 | I6: 4380 | J6: 1 | K6: 1 | L6: 1.793 | M6: 2918 | N6: 5304 | O6: 95 | P6: 1144 | Q6: 0 | R6: 0 | S6: 0 | T6: 0 | U6: 0
A7: 5 | B7: Babungwe | C7: Homme | D7: 9 | E7: 2 | F7: 550 | G7: 2.75 | H7: 2545 | I7: 3942 | J7: 0 | K7: 0 | L7: 0.775 | M7: 250 | N7: 2670 | O7: 0 | P7: -125 | Q7: 0 | R7: 0 | S7: 0 | T7: 0 | U7: 0
A8: 6 | B8: Babungwe | C8: Homme | D8: 5 | E8: 2 | F8: 290 | G8: 3.625 | H8: 1652 | I8: 2190 | J8: 0 | K8: 0 | L8: 0.905 | M8: 542 | N8: 907 | O8: 0 | P8: 675 | Q8: 70 | R8: 0 | S8: 0 | T8: 0 | U8: 0
A9: 7 | B9: Babungwe | C9: Homme | D9: 9 | E9: 4 | F9: 450 | G9: 3.539 | H9: 1905 | I9: 3942 | J9: 0 | K9: 0 | L9: 0.58 | M9: 780 | N9: 1955 | O9: 0 | P9: 0 | Q9: -50 | R9: 0 | S9: 0 | T9: 0 | U9: 0
A10: 8 | B10: Babungwe | C10: Homme | D10: 14 | E10: 7 | F10: 750 | G10: 3.75 | H10: 4975 | I10: 6132 | J10: 1 | K10: 0 | L10: 0.974 | M10: 3 | N10: 4640 | O10: 0 | P10: 335 | Q10: 0 | R10: 0 | S10: 0 | T10: 0 | U10: 0
A11: 9 | B11: Babungwe | C11: Femme | D11: 9 | E11: 2 | F11: 75 | G11: 3.75 | H11: 461.5 | I11: 3942 | J11: 0 | K11: 0 | L11: 0.14 | M11: -413.5 | N11: 176.5 | O11: 0 | P11: 285 | Q11: 0 | R11: 0 | S11: 0 | T11: 0 | U11: 0
A12: 10 | B12: Babungwe | C12: Homme | D12: 10 | E12: 4 | F12: 300 | G12: 3.592 | H12: 3140 | I12: 4380 | J12: 1 | K12: 0 | L12: 0.86 | M12: 755 | N12: 3190 | O12: 0 | P12: 0 | Q12: -50 | R12: 0 | S12: 0 | T12: 0 | U12: 0
A13: 11 | B13: Babungwe | C13: Femme | D13: 6 | E13: 1 | F13: 140 | G13: 3.5 | H13: 403 | I13: 2628 | J13: 0 | K13: 0 | L13: 0.184 | M13: -614 | N13: 228 | O13: 0 | P13: 185 | Q13: -10 | R13: 0 | S13: 0 | T13: 0 | U13: 0
A14: 12 | B14: Babungwe | C14: Homme | D14: 8 | E14: 2.5 | F14: 300 | G14: 3.621 | H14: 2975 | I14: 3504 | J14: 1 | K14: 0 | L14: 1.019 | M14: 360 | N14: 835 | O14: 0 | P14: 2150 | Q14: -10 | R14: 0 | S14: 0 | T14: 0 | U14: 0
... A90: 88 | B90: Mayuano | C90: Homme | D90: 10 | E90: 9 | F90: 800 | G90: 2.5 | H90: 8515 | I90: 4380 | J90: 1 | K90: 1 | L90: 2.333 | M90: 6175 | N90: 7751 | O90: 0 | P90: 0 | Q90: -36 | R90: 0 | S90: 600 | T90: 200 | U90: 0
A92: Revenu net = somme des 7 sources. La variable « living_income » du questionnaire vaut revenu − dépenses : elle n'est pas utilisée comme revenu.

Sheet Okapi
A1: Base planteurs Cacao Okapi (301 planteurs, liste 2024)
A3: Section | B3: Planteurs | C3: Superficie totale (ha) | D3: Superficie cacao (ha) | E3: Ha cacao / planteur | F3: Part du foncier en cacao
A4: Bahaha | B4: 32 | C4: 177.5 | D4: 70.5 | E4: =D4/B4 -> 2.203125 | F4: =D4/C4 -> 0.3971831
A5: Kilimamwenza | B5: 11 | C5: 42 | D5: 22 | E5: =D5/B5 -> 2 | F5: =D5/C5 -> 0.52380952
A6: Mambasa | B6: 73 | C6: 338 | D6: 119 | E6: =D6/B6 -> 1.630137 | F6: =D6/C6 -> 0.35207101
A7: Mayuano | B7: 85 | C7: 326 | D7: 142 | E7: =D7/B7 -> 1.6705882 | F7: =D7/C7 -> 0.43558282
A8: Mungamba | B8: 100 | C8: 335.25 | D8: 169.5 | E8: =D8/B8 -> 1.695 | F8: =D8/C8 -> 0.50559284
A9: Total | B9: =SUM(B4:B8) -> 301 | C9: =SUM(C4:C8) -> 1218.75 | D9: =SUM(D4:D8) -> 523 | E9: =D9/B9 -> 1.7375415 | F9: =D9/C9 -> 0.42912821
A11: Nombre de tiges estimé (≈ superficie × 1 100) pour 76 % des planteurs : à recompter lors du prochain inventaire.

Sheet Qualité
A1: Registre des contrôles qualité — base du PV de validation
A2: Avis proposé : validation partielle. Valider la base café comme référentiel des bénéficiaires, pas pour ses indicateurs économiques.
A3: ID | B3: Base | C3: Dimension | D3: Contrôle | E3: Anomalies | F3: Total contrôlé | G3: Taux | H3: Gravité | I3: Impact / commentaire
A4: 9 | B4: Café Rikolto | C4: Validité | D4: Production = superficie × densité × rendement/pied (paramètres fixes) | E4: 42433 | F4: 42433 | G4: =IFERROR(E4/F4,0) -> 1 | H4: Critique | I4: Production estimée, non mesurée
A5: 10 | B5: Café Rikolto | C5: Validité | D5: Chiffre d'affaires = production × 0,55 USD (prix unique 2019-2025) | E5: 42433 | F5: 42433 | G5: =IFERROR(E5/F5,0) -> 1 | H5: Critique | I5: Le CA ne reflète pas les prix réels
A6: 11 | B6: Café Rikolto | C6: Validité | D6: Coût = 40 % du CA et marge = 60 % du CA | E6: 42433 | F6: 42433 | G6: =IFERROR(E6/F6,0) -> 1 | H6: Critique | I6: Marge forfaitaire, pas de coûts réels
A7: 16 | B7: Cacao LI | C7: Validité | D7: Variable « living_income » = revenu − dépenses (et non le revenu) | E7: 88 | F7: 88 | G7: =IFERROR(E7/F7,0) -> 1 | H7: Critique | I7: Mal nommée : sous-estime fortement le revenu si lue telle quelle
A8: 1 | B8: Café Rikolto | C8: Complétude | D8: Territoire manquant | E8: 15430 | F8: 42433 | G8: =IFERROR(E8/F8,0) -> 0.36363208 | H8: Élevée | I8: Empêche une analyse géographique fiable
A9: 4 | B9: Café Rikolto | C9: Complétude | D9: Statut de certification manquant | E9: 6016 | F9: 42433 | G9: =IFERROR(E9/F9,0) -> 0.14177645 | H9: Élevée | I9: Concentré sur 2022 et 2024
A10: 7 | B10: Café Rikolto | C10: Unicité | D10: N° de carte membre en doublon sur une même campagne | E10: 2099 | F10: 42433 | G10: =IFERROR(E10/F10,0) -> 0.049466217 | H10: Élevée | I10: Risque de double comptage ou cartes réattribuées
A11: 12 | B11: Café Rikolto | C11: Validité | D11: « Prix unitaire » identique au taux de transformation cerise→parche | E11: 38250 | F11: 42433 | G11: =IFERROR(E11/F11,0) -> 0.90142106 | H11: Élevée | I11: Colonne probablement mal alimentée
A12: 13 | B12: Café Rikolto | C12: Cohérence | D12: Marge/ha négative alors que la marge totale est positive | E12: 8047 | F12: 42433 | G12: =IFERROR(E12/F12,0) -> 0.18964014 | H12: Élevée | I12: Deux modèles économiques contradictoires (2019-2020)
A13: 15 | B13: Café Rikolto | C13: Cohérence | D13: Rupture de série 2024 : +4 922 nouveaux producteurs | E13: 4922 | F13: 9326 | G13: =IFERROR(E13/F13,0) -> 0.52777182 | H13: Élevée | I13: Intégration de COOPADE puis COOKURU (2025)
A14: 20 | B14: Cacao LI | C14: Représentativité | D14: Échantillon de 88 ménages dont 6 femmes | E14: 6 | F14: 88 | G14: =IFERROR(E14/F14,0) -> 0.068181818 | H14: Élevée | I14: Résultats indicatifs ; ne pas extrapoler par sous-groupe
A15: 2 | B15: Café Rikolto | C15: Complétude | D15: Collectivité manquante | E15: 19237 | F15: 42433 | G15: =IFERROR(E15/F15,0) -> 0.45334999 | H15: Moyenne
A16: 3 | B16: Café Rikolto | C16: Complétude | D16: Village manquant | E16: 9454 | F16: 42433 | G16: =IFERROR(E16/F16,0) -> 0.22279829 | H16: Moyenne
A17: 8 | B17: Café Rikolto | C17: Cohérence | D17: Âge incohérent d'une année à l'autre (écart > 2 ans) | E17: 2305 | F17: 29252 | G17: =IFERROR(E17/F17,0) -> 0.078798031 | H17: Moyenne | I17: L'identifiant longitudinal peut regrouper des personnes différentes
A18: 14 | B18: Café Rikolto | C18: Cohérence | D18: Petite + grande saison ≠ production totale | E18: 4183 | F18: 42433 | G18: =IFERROR(E18/F18,0) -> 0.098578936 | H18: Moyenne
A19: 19 | B19: Cacao LI | C19: Validité | D19: Valeurs extrêmes (revenu, rendement ou prix) | E19: 6 | F19: 88 | G19: =IFERROR(E19/F19,0) -> 0.068181818 | H19: Moyenne | I19: Ex. 44 ha, 15 t, revenu 59 705 USD : à vérifier sur le terrain
A20: 21 | B20: Cacao Okapi | C20: Unicité | D20: Code planteur en doublon | E20: 28 | F20: 301 | G20: =IFERROR(E20/F20,0) -> 0.093023256 | H20: Moyenne
A21: 22 | B21: Cacao Okapi | C21: Cohérence | D21: Superficie cacao > superficie totale | E21: 4 | F21: 301 | G21: =IFERROR(E21/F21,0) -> 0.013289037 | H21: Moyenne
A22: 23 | B22: Cacao Okapi | C22: Validité | D22: Nb de tiges ≈ superficie × 1 100 (estimé, non compté) | E22: 228 | F22: 301 | G22: =IFERROR(E22/F22,0) -> 0.75747508 | H22: Moyenne
A23: 5 | B23: Café Rikolto | C23: Complétude | D23: Année d'adhésion à l'OP manquante | E23: 12255 | F23: 42433 | G23: =IFERROR(E23/F23,0) -> 0.28880824 | H23: Faible
A24: 6 | B24: Café Rikolto | C24: Complétude | D24: Âge manquant | E24: 441 | F24: 42433 | G24: =IFERROR(E24/F24,0) -> 0.010392855 | H24: Faible
A25: 17 | B25: Cacao LI | C25: Complétude | D25: Questionnaires sans consentement / vides | E25: 2 | F25: 90 | G25: =IFERROR(E25/F25,0) -> 0.022222222 | H25: Faible | I25: Exclus de l'analyse
A26: 18 | B26: Cacao LI | C26: Cohérence | D26: Noms de municipalité non normalisés (Mambas, Mayuwano…) | E26: 3 | F26: 88 | G26: =IFERROR(E26/F26,0) -> 0.034090909 | H26: Faible | I26: Corrigés
A28: Détail : data/qualite_controles.csv. Le taux se recalcule à partir des colonnes Anomalies et Total.

Sheet Paramètres
A1: Paramètres utilisés
A3: Paramètre | B3: Valeur | C3: Source
A4: Seuil revenu vital ménage (USD/an) | B4: 2628 | C4: Anker Research Institute, Living Income Reference Value RDC rurale, mise à jour 2025 (219 USD/mois, ménage de référence 6 personnes)
A5: Taille ménage de référence | B5: 6 | C5: Anker Research Institute, rapport 2021
A6: Seuil pauvreté extrême (USD/pers/jour) | B6: 2.15 | C6: Banque mondiale, PPA 2017
A7: Seuil minimal N-1 pour calculer la rétention | B7: 30 | C7: Hypothèse d'analyse : en dessous, la coopérative est considérée comme nouvelle
